
{
    "$schema": "https://schema.freqtrade.io/schema.json",
    "max_open_trades": 3,
    "stake_currency": "USDT",
    "stake_amount": "unlimited",
    "tradable_balance_ratio": 0.99,
    "fiat_display_currency": "USD",
    "dry_run": true,
    "dry_run_wallet": 1000,
    "cancel_open_orders_on_exit": false,
    "trading_mode": "spot",
    "margin_mode": "",
    "unfilledtimeout": {
        "entry": 10,
        "exit": 10,
        "exit_timeout_count": 0,
        "unit": "minutes"
    },
    "entry_pricing": {
        "price_side": "same",
        "use_order_book": true,
        "order_book_top": 1,
        "price_last_balance": 0.0,
        "check_depth_of_market": {
            "enabled": false,
            "bids_to_ask_delta": 1
        }
    },
    "exit_pricing":{
        "price_side": "same",
        "use_order_book": true,
        "order_book_top": 1
    },
    "exchange": {
        "name": "okx",
        "key": "ak-d8a5653d-6067-46ac-baa8-a65dc47d089a",
        "secret": "bLGRtIYA6mrEWnEQ7pfKJ7867D5X4ttyc1NmS8h1JbFXYEnt7aN5w5Ogh5Ey2NUv",
        "ccxt_config": {},
        "ccxt_async_config": {},
        "pair_whitelist": [
        ],
        "pair_blacklist": [
        ]
    },
    "pairlists": [
        {
            "method": "VolumePairList",
            "number_assets": 20,
            "sort_key": "quoteVolume",
            "min_value": 0,
            "refresh_period": 1800
        }
    ],
    "telegram": {
        "enabled": false,
        "token": "",
        "chat_id": ""
    },
    "api_server": {
        "enabled": true,
        "listen_ip_address": "127.0.0.1",
        "listen_port": 8080,
        "verbosity": "error",
        "enable_openapi": false,
        "jwt_secret_key": "aeda24b9dd1e0cb5da5d88c24581e71ccaab7f20fe01d8844897032ab359b008",
        "ws_token": "zlS7SRpEzv8CteYk-D41HfIDrUKRq_ItHw",
        "CORS_origins": [],
        "username": "freqtrader",
        "password": ""
    },
    "bot_name": "freqtrade",
    "initial_state": "running",
    "force_entry_enable": false,
    "internals": {
        "process_throttle_secs": 5
    }
}
