{
"telegram": {
        "enabled": false,
        "token": "",
        "chat_id": ""
    },
    "api_server": {
        "enabled": true,
        "listen_ip_address": "127.0.0.1",
        "listen_port": 8080,
        "verbosity": "error",
        "enable_openapi": false,
        "jwt_secret_key": "",
        "ws_token": "",
        "CORS_origins": [],
        "username": "a",
        "password": "a"
    },
    "bot_name": "freqtrade",
    "initial_state": "running",
    "force_entry_enable": true,
    "internals": {
        "process_throttle_secs": 5
    }
}